pylordeckcodes/__init__.py
pylordeckcodes/card_code_and_count.py
pylordeckcodes/lor_deck_encoder.py
pylordeckcodes/varint_translator.py
pylordeckcodes-1.0.0.dist-info/LICENSE
pylordeckcodes-1.0.0.dist-info/METADATA
pylordeckcodes-1.0.0.dist-info/WHEEL
pylordeckcodes-1.0.0.dist-info/top_level.txt
pylordeckcodes-1.0.0.dist-info/RECORD
