Metadata-Version: 2.1
Name: pylordeckcodes
Version: 1.0.0
Summary: A python implementation for the Legends of Runeterra deck encoder/decoder, originally written in C# by Riot Games.
Home-page: https://github.com/Bamiji/PyLoRDeckCodes
Author: Bamiji
Author-email: banji@banjislab.com
License: UNKNOWN
Platform: UNKNOWN
Classifier: Programming Language :: Python :: 3
Classifier: License :: OSI Approved :: Apache Software License
Classifier: Operating System :: OS Independent
Requires-Python: >=3.6
